clibb/Application.py
clibb/Color.py
clibb/Mutable.py
clibb/Window.py
clibb/__init__.py
clibb/elements/Action.py
clibb/elements/Checkbox.py
clibb/elements/Configuration.py
clibb/elements/Display.py
clibb/elements/Element.py
clibb/elements/Input.py
clibb/elements/Interactable.py
clibb/elements/Navigation.py
clibb/elements/Separator.py
clibb/elements/Title.py
clibb/elements/__init__.py
clibb-0.3.0.dist-info/LICENSE
clibb-0.3.0.dist-info/METADATA
clibb-0.3.0.dist-info/WHEEL
clibb-0.3.0.dist-info/top_level.txt
clibb-0.3.0.dist-info/RECORD
