Metadata-Version: 2.1
Name: clibb
Version: 0.3.0
Summary: CLIBB (Command-Line Interface Building Blocks) streamlines, simplifies and speeds up your CLI creation.
Home-page: https://github.com/Dreamfarer/clibb
Author: Dreamfarer
Classifier: Programming Language :: Python :: 3
Classifier: License :: OSI Approved :: GNU Affero General Public License v3
Classifier: Operating System :: OS Independent
Requires-Python: >=3.10
License-File: LICENSE
